BlockRAM.v
`timescale 1ns / 1ps
module BlockRAM #( parameter DATA_WIDTH = 32, ADDRESS_WIDTH = 12, DEPTH = 4096, MEMFILE = "dataMem.mem") (
    input wire                     clk,
    input wire                     wEn,
    input wire [ADDRESS_WIDTH-1:0] addr1,
    input wire [ADDRESS_WIDTH-1:0] addr2,
    input wire [DATA_WIDTH-1:0]    dataIn,
    output wire [DATA_WIDTH-1:0]    dataOut1,
    output wire [DATA_WIDTH-1:0]    dataOut2,
    input wire [31:0] checkID,
    input wire nowCheck
    ); //VGA read
    
    reg[DATA_WIDTH-1:0] MemoryArray[0:DEPTH-1];

    initial begin
        if(MEMFILE > 0) begin
            $readmemh(MEMFILE, MemoryArray);
        end
    end
    
    assign isBomb = MemoryArray[checkID]==32'd11;
    always @(negedge clk) begin
        if(wEn) begin
            MemoryArray[addr1] = dataIn;
        end
        if(nowCheck) begin
            MemoryArray[checkID] = numArray[checkID];
        end

    end

    assign dataOut1 = MemoryArray[addr1];
    assign dataOut2 = MemoryArray[addr2];

    wire [31:0] numArray[24:0];

    assign numArray[0] = (MemoryArray[1]==32'd10) + (MemoryArray[6]==32'd10) + (MemoryArray[5]==32'd10);
    assign numArray[4] = (MemoryArray[3]==32'd10) + (MemoryArray[8]==32'd10) + (MemoryArray[9]==32'd10);
    assign numArray[20] = (MemoryArray[15]==32'd10) + (MemoryArray[16]==32'd10) + (MemoryArray[21]==32'd10);
    assign numArray[24] = (MemoryArray[18]==32'd10) + (MemoryArray[19]==32'd10) + (MemoryArray[23]==32'd10);

    genvar i;
    generate
        for(i=1; i<4; i=i+1) begin: loopi
            assign numArray[i] = (MemoryArray[i-1]==32'd10) + (MemoryArray[i+1]==32'd10) + (MemoryArray[i+5]==32'd10)+ (MemoryArray[i+4]==32'd10)+ (MemoryArray[i+6]==32'd10);
            assign numArray[20+i] = (MemoryArray[20+i-1]==32'd10) + (MemoryArray[20+i+1]==32'd10) + (MemoryArray[20+i-5]==32'd10)+ (MemoryArray[20+i-4]==32'd10)+ (MemoryArray[20+i-6]==32'd10);
        end 
    endgenerate

    genvar j;
    generate
        for(j=1; j<4; j=j+1) begin: loopj
            assign numArray[j*5] = (MemoryArray[5*(j-1)]==32'd10) + (MemoryArray[5*(j+1)]==32'd10)+ (MemoryArray[5*(j-1)+1]==32'd10)+ (MemoryArray[5*(j+1)+1]==32'd10) + (MemoryArray[5*j+1]==32'd10);
            assign numArray[j*5+4] = (MemoryArray[5*(j-1)+4]==32'd10) + (MemoryArray[5*(j+1)+4]==32'd10)+ (MemoryArray[5*(j-1)+3]==32'd10)+ (MemoryArray[5*(j+1)+3]==32'd10) + (MemoryArray[5*j+3]==32'd10);
        end 
    endgenerate

    genvar m,n;
    generate
        for(m=1; m<4; m=m+1) begin: loopm
            for(n=1; n<4; n=n+1) begin: loopn
            assign numArray[m*5+n] = (MemoryArray[5*(m-1)+n]==32'd10) + (MemoryArray[5*(m+1)+n]==32'd10)+ (MemoryArray[5*(m-1)+n+1]==32'd10)+ (MemoryArray[5*(m+1)+n+1]==32'd10) + (MemoryArray[5*m+n+1]==32'd10)+ (MemoryArray[5*(m-1)+n-1]==32'd10)+ (MemoryArray[5*(m+1)+n-1]==32'd10) + (MemoryArray[5*m+n-1]==32'd10);
            end
        end 
    endgenerate
    

    // always @(negedge clk) begin
    //       $display("%d,     %d,     %d",numArray[0][0], numArray[0][1], numArray[4][2]);
    //   end
endmodule

BlockRAM_tb.v
module BlockRAM_tb();
    reg                     clk;
    reg                     wEn;
    reg [11:0] addr1;
    reg [11:0] addr2;
    reg [31:0]    dataIn, checkID;
    reg nowCheck;

    BlockRAM testRAM(.clk(clk), .wEn(wEn), .addr1(addr1), .addr2(addr2), .dataIn(dataIn), .checkID(checkID), .nowCheck(nowCheck));
    initial begin
        clk = 0;
        wEn = 0;
        addr1 = 12'b0;
        addr2 = 12'b0;
        dataIn = 31'b0;
        nowCheck = 0;
        checkID = 32'd5;

        #20
        nowCheck = 1;
        #30
        nowCheck = 0;
        #40
        checkID = 32'd16;
        #60
        nowCheck = 1;

        //Set a time delay, in nanoseconds
        #8000;

        //Ends the testbench
        $finish;
    end

    always  
        #10 clk = ~clk;

    // integer i, j;
    initial begin
        //output filename
        $dumpfile("BlockRAM_tb.vcd");
        // Module to capture and what level, 0 means all wires
        //$dumpvars(0, BlockRAM_tb);
        // for(i = 0; i < 5; i = i + 1)
        //     $dumpvars(1, BlockRAM_tb.testRAM.BlockRAM.numArray[i][0]);
        //     $dumpvars(1, BlockRAM_tb.testRAM.BlockRAM.numArray[i][0]);
        
        // for (i = 0; i < 5; i = i + 1) begin
        //     for (j = 0; j < 5; j = j + 1) begin
        //         $dumpvars(0, BlockRAM_tb.testRAM.BlockRAM.numArray[i][j]);
        //     end
        // end
        $dumpvars(0, BlockRAM_tb.testRAM.BlockRAM.MemoryArray[0]);
        $dumpvars(0, BlockRAM_tb.testRAM.BlockRAM.MemoryArray[1]);
        $dumpvars(0, BlockRAM_tb.testRAM.BlockRAM.MemoryArray[2]);
        $dumpvars(0, BlockRAM_tb.testRAM.BlockRAM.MemoryArray[3]);
        $dumpvars(0, BlockRAM_tb.testRAM.BlockRAM.MemoryArray[4]);
        $dumpvars(0, BlockRAM_tb.testRAM.BlockRAM.MemoryArray[5]);
        $dumpvars(0, BlockRAM_tb.testRAM.BlockRAM.MemoryArray[6]);
        $dumpvars(0, BlockRAM_tb.testRAM.BlockRAM.MemoryArray[7]);
        $dumpvars(0, BlockRAM_tb.testRAM.BlockRAM.MemoryArray[8]);
        $dumpvars(0, BlockRAM_tb.testRAM.BlockRAM.MemoryArray[9]);
        $dumpvars(0, BlockRAM_tb.testRAM.BlockRAM.MemoryArray[10]);
        $dumpvars(0, BlockRAM_tb.testRAM.BlockRAM.MemoryArray[11]);
        $dumpvars(0, BlockRAM_tb.testRAM.BlockRAM.MemoryArray[12]);
        $dumpvars(0, BlockRAM_tb.testRAM.BlockRAM.MemoryArray[13]);
        $dumpvars(0, BlockRAM_tb.testRAM.BlockRAM.MemoryArray[14]);
        $dumpvars(0, BlockRAM_tb.testRAM.BlockRAM.MemoryArray[15]);
        $dumpvars(0, BlockRAM_tb.testRAM.BlockRAM.MemoryArray[16]);
        $dumpvars(0, BlockRAM_tb.testRAM.BlockRAM.MemoryArray[17]);
        $dumpvars(0, BlockRAM_tb.testRAM.BlockRAM.MemoryArray[18]);
        $dumpvars(0, BlockRAM_tb.testRAM.BlockRAM.MemoryArray[19]);
        $dumpvars(0, BlockRAM_tb.testRAM.BlockRAM.MemoryArray[20]);
        $dumpvars(0, BlockRAM_tb.testRAM.BlockRAM.MemoryArray[21]);
        $dumpvars(0, BlockRAM_tb.testRAM.BlockRAM.MemoryArray[22]);
        $dumpvars(0, BlockRAM_tb.testRAM.BlockRAM.MemoryArray[23]);
        $dumpvars(0, BlockRAM_tb.testRAM.BlockRAM.MemoryArray[24]);

        $dumpvars(0, BlockRAM_tb.testRAM.BlockRAM.numArray[0]);
        $dumpvars(0, BlockRAM_tb.testRAM.BlockRAM.numArray[1]);
        $dumpvars(0, BlockRAM_tb.testRAM.BlockRAM.numArray[2]);
        $dumpvars(0, BlockRAM_tb.testRAM.BlockRAM.numArray[3]);
        $dumpvars(0, BlockRAM_tb.testRAM.BlockRAM.numArray[4]);
        $dumpvars(0, BlockRAM_tb.testRAM.BlockRAM.numArray[5]);
        $dumpvars(0, BlockRAM_tb.testRAM.BlockRAM.numArray[6]);
        $dumpvars(0, BlockRAM_tb.testRAM.BlockRAM.numArray[7]);
        $dumpvars(0, BlockRAM_tb.testRAM.BlockRAM.numArray[8]);
        $dumpvars(0, BlockRAM_tb.testRAM.BlockRAM.numArray[9]);
        $dumpvars(0, BlockRAM_tb.testRAM.BlockRAM.numArray[10]);
        $dumpvars(0, BlockRAM_tb.testRAM.BlockRAM.numArray[11]);
        $dumpvars(0, BlockRAM_tb.testRAM.BlockRAM.numArray[12]);
        $dumpvars(0, BlockRAM_tb.testRAM.BlockRAM.numArray[13]);
        $dumpvars(0, BlockRAM_tb.testRAM.BlockRAM.numArray[14]);
        $dumpvars(0, BlockRAM_tb.testRAM.BlockRAM.numArray[15]);
        $dumpvars(0, BlockRAM_tb.testRAM.BlockRAM.numArray[16]);
        $dumpvars(0, BlockRAM_tb.testRAM.BlockRAM.numArray[17]);
        $dumpvars(0, BlockRAM_tb.testRAM.BlockRAM.numArray[18]);
        $dumpvars(0, BlockRAM_tb.testRAM.BlockRAM.numArray[19]);
        $dumpvars(0, BlockRAM_tb.testRAM.BlockRAM.numArray[20]);
        $dumpvars(0, BlockRAM_tb.testRAM.BlockRAM.numArray[21]);
        $dumpvars(0, BlockRAM_tb.testRAM.BlockRAM.numArray[22]);
        $dumpvars(0, BlockRAM_tb.testRAM.BlockRAM.numArray[23]);
        $dumpvars(0, BlockRAM_tb.testRAM.BlockRAM.numArray[24]);
        $dumpvars(0, BlockRAM_tb);
    end
endmodule

BlockRAM_tb.vcd
$date
	Sun Nov  8 15:19:58 2020
$end
$version
	Icarus Verilog
$end
$timescale
	1ps
$end
$scope module BlockRAM_tb $end
$scope module testRAM $end
$var reg 32 ! \MemoryArray[0] [31:0] $end
$upscope $end
$upscope $end
$scope module BlockRAM_tb $end
$scope module testRAM $end
$var reg 32 " \MemoryArray[1] [31:0] $end
$upscope $end
$upscope $end
$scope module BlockRAM_tb $end
$scope module testRAM $end
$var reg 32 # \MemoryArray[2] [31:0] $end
$upscope $end
$upscope $end
$scope module BlockRAM_tb $end
$scope module testRAM $end
$var reg 32 $ \MemoryArray[3] [31:0] $end
$upscope $end
$upscope $end
$scope module BlockRAM_tb $end
$scope module testRAM $end
$var reg 32 % \MemoryArray[4] [31:0] $end
$upscope $end
$upscope $end
$scope module BlockRAM_tb $end
$scope module testRAM $end
$var reg 32 & \MemoryArray[5] [31:0] $end
$upscope $end
$upscope $end
$scope module BlockRAM_tb $end
$scope module testRAM $end
$var reg 32 ' \MemoryArray[6] [31:0] $end
$upscope $end
$upscope $end
$scope module BlockRAM_tb $end
$scope module testRAM $end
$var reg 32 ( \MemoryArray[7] [31:0] $end
$upscope $end
$upscope $end
$scope module BlockRAM_tb $end
$scope module testRAM $end
$var reg 32 ) \MemoryArray[8] [31:0] $end
$upscope $end
$upscope $end
$scope module BlockRAM_tb $end
$scope module testRAM $end
$var reg 32 * \MemoryArray[9] [31:0] $end
$upscope $end
$upscope $end
$scope module BlockRAM_tb $end
$scope module testRAM $end
$var reg 32 + \MemoryArray[10] [31:0] $end
$upscope $end
$upscope $end
$scope module BlockRAM_tb $end
$scope module testRAM $end
$var reg 32 , \MemoryArray[11] [31:0] $end
$upscope $end
$upscope $end
$scope module BlockRAM_tb $end
$scope module testRAM $end
$var reg 32 - \MemoryArray[12] [31:0] $end
$upscope $end
$upscope $end
$scope module BlockRAM_tb $end
$scope module testRAM $end
$var reg 32 . \MemoryArray[13] [31:0] $end
$upscope $end
$upscope $end
$scope module BlockRAM_tb $end
$scope module testRAM $end
$var reg 32 / \MemoryArray[14] [31:0] $end
$upscope $end
$upscope $end
$scope module BlockRAM_tb $end
$scope module testRAM $end
$var reg 32 0 \MemoryArray[15] [31:0] $end
$upscope $end
$upscope $end
$scope module BlockRAM_tb $end
$scope module testRAM $end
$var reg 32 1 \MemoryArray[16] [31:0] $end
$upscope $end
$upscope $end
$scope module BlockRAM_tb $end
$scope module testRAM $end
$var reg 32 2 \MemoryArray[17] [31:0] $end
$upscope $end
$upscope $end
$scope module BlockRAM_tb $end
$scope module testRAM $end
$var reg 32 3 \MemoryArray[18] [31:0] $end
$upscope $end
$upscope $end
$scope module BlockRAM_tb $end
$scope module testRAM $end
$var reg 32 4 \MemoryArray[19] [31:0] $end
$upscope $end
$upscope $end
$scope module BlockRAM_tb $end
$scope module testRAM $end
$var reg 32 5 \MemoryArray[20] [31:0] $end
$upscope $end
$upscope $end
$scope module BlockRAM_tb $end
$scope module testRAM $end
$var reg 32 6 \MemoryArray[21] [31:0] $end
$upscope $end
$upscope $end
$scope module BlockRAM_tb $end
$scope module testRAM $end
$var reg 32 7 \MemoryArray[22] [31:0] $end
$upscope $end
$upscope $end
$scope module BlockRAM_tb $end
$scope module testRAM $end
$var reg 32 8 \MemoryArray[23] [31:0] $end
$upscope $end
$upscope $end
$scope module BlockRAM_tb $end
$scope module testRAM $end
$var reg 32 9 \MemoryArray[24] [31:0] $end
$upscope $end
$upscope $end
$scope module BlockRAM_tb $end
$scope module testRAM $end
$var wire 32 : \numArray[0] [31:0] $end
$upscope $end
$upscope $end
$scope module BlockRAM_tb $end
$scope module testRAM $end
$var wire 32 ; \numArray[1] [31:0] $end
$upscope $end
$upscope $end
$scope module BlockRAM_tb $end
$scope module testRAM $end
$var wire 32 < \numArray[2] [31:0] $end
$upscope $end
$upscope $end
$scope module BlockRAM_tb $end
$scope module testRAM $end
$var wire 32 = \numArray[3] [31:0] $end
$upscope $end
$upscope $end
$scope module BlockRAM_tb $end
$scope module testRAM $end
$var wire 32 > \numArray[4] [31:0] $end
$upscope $end
$upscope $end
$scope module BlockRAM_tb $end
$scope module testRAM $end
$var wire 32 ? \numArray[5] [31:0] $end
$upscope $end
$upscope $end
$scope module BlockRAM_tb $end
$scope module testRAM $end
$var wire 32 @ \numArray[6] [31:0] $end
$upscope $end
$upscope $end
$scope module BlockRAM_tb $end
$scope module testRAM $end
$var wire 32 A \numArray[7] [31:0] $end
$upscope $end
$upscope $end
$scope module BlockRAM_tb $end
$scope module testRAM $end
$var wire 32 B \numArray[8] [31:0] $end
$upscope $end
$upscope $end
$scope module BlockRAM_tb $end
$scope module testRAM $end
$var wire 32 C \numArray[9] [31:0] $end
$upscope $end
$upscope $end
$scope module BlockRAM_tb $end
$scope module testRAM $end
$var wire 32 D \numArray[10] [31:0] $end
$upscope $end
$upscope $end
$scope module BlockRAM_tb $end
$scope module testRAM $end
$var wire 32 E \numArray[11] [31:0] $end
$upscope $end
$upscope $end
$scope module BlockRAM_tb $end
$scope module testRAM $end
$var wire 32 F \numArray[12] [31:0] $end
$upscope $end
$upscope $end
$scope module BlockRAM_tb $end
$scope module testRAM $end
$var wire 32 G \numArray[13] [31:0] $end
$upscope $end
$upscope $end
$scope module BlockRAM_tb $end
$scope module testRAM $end
$var wire 32 H \numArray[14] [31:0] $end
$upscope $end
$upscope $end
$scope module BlockRAM_tb $end
$scope module testRAM $end
$var wire 32 I \numArray[15] [31:0] $end
$upscope $end
$upscope $end
$scope module BlockRAM_tb $end
$scope module testRAM $end
$var wire 32 J \numArray[16] [31:0] $end
$upscope $end
$upscope $end
$scope module BlockRAM_tb $end
$scope module testRAM $end
$var wire 32 K \numArray[17] [31:0] $end
$upscope $end
$upscope $end
$scope module BlockRAM_tb $end
$scope module testRAM $end
$var wire 32 L \numArray[18] [31:0] $end
$upscope $end
$upscope $end
$scope module BlockRAM_tb $end
$scope module testRAM $end
$var wire 32 M \numArray[19] [31:0] $end
$upscope $end
$upscope $end
$scope module BlockRAM_tb $end
$scope module testRAM $end
$var wire 32 N \numArray[20] [31:0] $end
$upscope $end
$upscope $end
$scope module BlockRAM_tb $end
$scope module testRAM $end
$var wire 32 O \numArray[21] [31:0] $end
$upscope $end
$upscope $end
$scope module BlockRAM_tb $end
$scope module testRAM $end
$var wire 32 P \numArray[22] [31:0] $end
$upscope $end
$upscope $end
$scope module BlockRAM_tb $end
$scope module testRAM $end
$var wire 32 Q \numArray[23] [31:0] $end
$upscope $end
$upscope $end
$scope module BlockRAM_tb $end
$scope module testRAM $end
$var wire 32 R \numArray[24] [31:0] $end
$upscope $end
$upscope $end
$scope module BlockRAM_tb $end
$var reg 12 S addr1 [11:0] $end
$var reg 12 T addr2 [11:0] $end
$var reg 32 U checkID [31:0] $end
$var reg 1 V clk $end
$var reg 32 W dataIn [31:0] $end
$var reg 1 X nowCheck $end
$var reg 1 Y wEn $end
$scope module testRAM $end
$var wire 12 Z addr1 [11:0] $end
$var wire 12 [ addr2 [11:0] $end
$var wire 32 \ checkID [31:0] $end
$var wire 1 V clk $end
$var wire 32 ] dataIn [31:0] $end
$var wire 32 ^ dataOut1 [31:0] $end
$var wire 32 _ dataOut2 [31:0] $end
$var wire 1 X nowCheck $end
$var wire 1 Y wEn $end
$var wire 1 ` isBomb $end
$scope begin loopi[1] $end
$upscope $end
$scope begin loopi[2] $end
$upscope $end
$scope begin loopi[3] $end
$upscope $end
$scope begin loopj[1] $end
$upscope $end
$scope begin loopj[2] $end
$upscope $end
$scope begin loopj[3] $end
$upscope $end
$scope begin loopm[1] $end
$scope begin loopn[1] $end
$upscope $end
$scope begin loopn[2] $end
$upscope $end
$scope begin loopn[3] $end
$upscope $end
$upscope $end
$scope begin loopm[2] $end
$scope begin loopn[1] $end
$upscope $end
$scope begin loopn[2] $end
$upscope $end
$scope begin loopn[3] $end
$upscope $end
$upscope $end
$scope begin loopm[3] $end
$scope begin loopn[1] $end
$upscope $end
$scope begin loopn[2] $end
$upscope $end
$scope begin loopn[3] $end
$upscope $end
$upscope $end
$upscope $end
$upscope $end
$enddefinitions $end
#0
$dumpvars
0`
b1011 _
b1011 ^
b0 ]
b101 \
b0 [
b0 Z
0Y
0X
b0 W
0V
b101 U
b0 T
b0 S
b0 R
b10 Q
b10 P
b10 O
b1 N
b0 M
b10 L
b10 K
b11 J
b1 I
b0 H
b1 G
b1 F
b10 E
b1 D
b0 C
b0 B
b1 A
b10 @
b1 ?
b0 >
b0 =
b1 <
b1 ;
b10 :
b0 9
b1011 8
b1010 7
b1010 6
b1011 5
b1011 4
b1011 3
b1010 2
b1011 1
b1011 0
b1011 /
b1011 .
b1011 -
b1011 ,
b1011 +
b1011 *
b1011 )
b1011 (
b1011 '
b1010 &
b1011 %
b1011 $
b1011 #
b1010 "
b1011 !
$end
#10000000000000
1V
#20000000000000
b1 &
b1 :
b0 ;
b0 D
b1 @
b1 E
0V
1X
#30000000000000
1V
#40000000000000
b1 &
0V
#50000000000000
1V
0X
#60000000000000
0V
#70000000000000
1V
#80000000000000
0V
#90000000000000
1V
1`
b10000 U
b10000 \
#100000000000000
0V
#110000000000000
1V
#120000000000000
0V
#130000000000000
1V
#140000000000000
0V
#150000000000000
1V
1X
#160000000000000
b11 1
0`
0V
#170000000000000
1V
#180000000000000
b11 1
0V
#190000000000000
1V
#200000000000000
b11 1
0V
#210000000000000
1V
#220000000000000
b11 1
0V
#230000000000000
1V
#240000000000000
b11 1
0V
#250000000000000
1V
#260000000000000
b11 1
0V
#270000000000000
1V
#280000000000000
b11 1
0V
#290000000000000
1V
#300000000000000
b11 1
0V
#310000000000000
1V
#320000000000000
b11 1
0V
#330000000000000
1V
#340000000000000
b11 1
0V
#350000000000000
1V
#360000000000000
b11 1
0V
#370000000000000
1V
#380000000000000
b11 1
0V
#390000000000000
1V
#400000000000000
b11 1
0V
#410000000000000
1V
#420000000000000
b11 1
0V
#430000000000000
1V
#440000000000000
b11 1
0V
#450000000000000
1V
#460000000000000
b11 1
0V
#470000000000000
1V
#480000000000000
b11 1
0V
#490000000000000
1V
#500000000000000
b11 1
0V
#510000000000000
1V
#520000000000000
b11 1
0V
#530000000000000
1V
#540000000000000
b11 1
0V
#550000000000000
1V
#560000000000000
b11 1
0V
#570000000000000
1V
#580000000000000
b11 1
0V
#590000000000000
1V
#600000000000000
b11 1
0V
#610000000000000
1V
#620000000000000
b11 1
0V
#630000000000000
1V
#640000000000000
b11 1
0V
#650000000000000
1V
#660000000000000
b11 1
0V
#670000000000000
1V
#680000000000000
b11 1
0V
#690000000000000
1V
#700000000000000
b11 1
0V
#710000000000000
1V
#720000000000000
b11 1
0V
#730000000000000
1V
#740000000000000
b11 1
0V
#750000000000000
1V
#760000000000000
b11 1
0V
#770000000000000
1V
#780000000000000
b11 1
0V
#790000000000000
1V
#800000000000000
b11 1
0V
#810000000000000
1V
#820000000000000
b11 1
0V
#830000000000000
1V
#840000000000000
b11 1
0V
#850000000000000
1V
#860000000000000
b11 1
0V
#870000000000000
1V
#880000000000000
b11 1
0V
#890000000000000
1V
#900000000000000
b11 1
0V
#910000000000000
1V
#920000000000000
b11 1
0V
#930000000000000
1V
#940000000000000
b11 1
0V
#950000000000000
1V
#960000000000000
b11 1
0V
#970000000000000
1V
#980000000000000
b11 1
0V
#990000000000000
1V
#1000000000000000
b11 1
0V
#1010000000000000
1V
#1020000000000000
b11 1
0V
#1030000000000000
1V
#1040000000000000
b11 1
0V
#1050000000000000
1V
#1060000000000000
b11 1
0V
#1070000000000000
1V
#1080000000000000
b11 1
0V
#1090000000000000
1V
#1100000000000000
b11 1
0V
#1110000000000000
1V
#1120000000000000
b11 1
0V
#1130000000000000
1V
#1140000000000000
b11 1
0V
#1150000000000000
1V
#1160000000000000
b11 1
0V
#1170000000000000
1V
#1180000000000000
b11 1
0V
#1190000000000000
1V
#1200000000000000
b11 1
0V
#1210000000000000
1V
#1220000000000000
b11 1
0V
#1230000000000000
1V
#1240000000000000
b11 1
0V
#1250000000000000
1V
#1260000000000000
b11 1
0V
#1270000000000000
1V
#1280000000000000
b11 1
0V
#1290000000000000
1V
#1300000000000000
b11 1
0V
#1310000000000000
1V
#1320000000000000
b11 1
0V
#1330000000000000
1V
#1340000000000000
b11 1
0V
#1350000000000000
1V
#1360000000000000
b11 1
0V
#1370000000000000
1V
#1380000000000000
b11 1
0V
#1390000000000000
1V
#1400000000000000
b11 1
0V
#1410000000000000
1V
#1420000000000000
b11 1
0V
#1430000000000000
1V
#1440000000000000
b11 1
0V
#1450000000000000
1V
#1460000000000000
b11 1
0V
#1470000000000000
1V
#1480000000000000
b11 1
0V
#1490000000000000
1V
#1500000000000000
b11 1
0V
#1510000000000000
1V
#1520000000000000
b11 1
0V
#1530000000000000
1V
#1540000000000000
b11 1
0V
#1550000000000000
1V
#1560000000000000
b11 1
0V
#1570000000000000
1V
#1580000000000000
b11 1
0V
#1590000000000000
1V
#1600000000000000
b11 1
0V
#1610000000000000
1V
#1620000000000000
b11 1
0V
#1630000000000000
1V
#1640000000000000
b11 1
0V
#1650000000000000
1V
#1660000000000000
b11 1
0V
#1670000000000000
1V
#1680000000000000
b11 1
0V
#1690000000000000
1V
#1700000000000000
b11 1
0V
#1710000000000000
1V
#1720000000000000
b11 1
0V
#1730000000000000
1V
#1740000000000000
b11 1
0V
#1750000000000000
1V
#1760000000000000
b11 1
0V
#1770000000000000
1V
#1780000000000000
b11 1
0V
#1790000000000000
1V
#1800000000000000
b11 1
0V
#1810000000000000
1V
#1820000000000000
b11 1
0V
#1830000000000000
1V
#1840000000000000
b11 1
0V
#1850000000000000
1V
#1860000000000000
b11 1
0V
#1870000000000000
1V
#1880000000000000
b11 1
0V
#1890000000000000
1V
#1900000000000000
b11 1
0V
#1910000000000000
1V
#1920000000000000
b11 1
0V
#1930000000000000
1V
#1940000000000000
b11 1
0V
#1950000000000000
1V
#1960000000000000
b11 1
0V
#1970000000000000
1V
#1980000000000000
b11 1
0V
#1990000000000000
1V
#2000000000000000
b11 1
0V
#2010000000000000
1V
#2020000000000000
b11 1
0V
#2030000000000000
1V
#2040000000000000
b11 1
0V
#2050000000000000
1V
#2060000000000000
b11 1
0V
#2070000000000000
1V
#2080000000000000
b11 1
0V
#2090000000000000
1V
#2100000000000000
b11 1
0V
#2110000000000000
1V
#2120000000000000
b11 1
0V
#2130000000000000
1V
#2140000000000000
b11 1
0V
#2150000000000000
1V
#2160000000000000
b11 1
0V
#2170000000000000
1V
#2180000000000000
b11 1
0V
#2190000000000000
1V
#2200000000000000
b11 1
0V
#2210000000000000
1V
#2220000000000000
b11 1
0V
#2230000000000000
1V
#2240000000000000
b11 1
0V
#2250000000000000
1V
#2260000000000000
b11 1
0V
#2270000000000000
1V
#2280000000000000
b11 1
0V
#2290000000000000
1V
#2300000000000000
b11 1
0V
#2310000000000000
1V
#2320000000000000
b11 1
0V
#2330000000000000
1V
#2340000000000000
b11 1
0V
#2350000000000000
1V
#2360000000000000
b11 1
0V
#2370000000000000
1V
#2380000000000000
b11 1
0V
#2390000000000000
1V
#2400000000000000
b11 1
0V
#2410000000000000
1V
#2420000000000000
b11 1
0V
#2430000000000000
1V
#2440000000000000
b11 1
0V
#2450000000000000
1V
#2460000000000000
b11 1
0V
#2470000000000000
1V
#2480000000000000
b11 1
0V
#2490000000000000
1V
#2500000000000000
b11 1
0V
#2510000000000000
1V
#2520000000000000
b11 1
0V
#2530000000000000
1V
#2540000000000000
b11 1
0V
#2550000000000000
1V
#2560000000000000
b11 1
0V
#2570000000000000
1V
#2580000000000000
b11 1
0V
#2590000000000000
1V
#2600000000000000
b11 1
0V
#2610000000000000
1V
#2620000000000000
b11 1
0V
#2630000000000000
1V
#2640000000000000
b11 1
0V
#2650000000000000
1V
#2660000000000000
b11 1
0V
#2670000000000000
1V
#2680000000000000
b11 1
0V
#2690000000000000
1V
#2700000000000000
b11 1
0V
#2710000000000000
1V
#2720000000000000
b11 1
0V
#2730000000000000
1V
#2740000000000000
b11 1
0V
#2750000000000000
1V
#2760000000000000
b11 1
0V
#2770000000000000
1V
#2780000000000000
b11 1
0V
#2790000000000000
1V
#2800000000000000
b11 1
0V
#2810000000000000
1V
#2820000000000000
b11 1
0V
#2830000000000000
1V
#2840000000000000
b11 1
0V
#2850000000000000
1V
#2860000000000000
b11 1
0V
#2870000000000000
1V
#2880000000000000
b11 1
0V
#2890000000000000
1V
#2900000000000000
b11 1
0V
#2910000000000000
1V
#2920000000000000
b11 1
0V
#2930000000000000
1V
#2940000000000000
b11 1
0V
#2950000000000000
1V
#2960000000000000
b11 1
0V
#2970000000000000
1V
#2980000000000000
b11 1
0V
#2990000000000000
1V
#3000000000000000
b11 1
0V
#3010000000000000
1V
#3020000000000000
b11 1
0V
#3030000000000000
1V
#3040000000000000
b11 1
0V
#3050000000000000
1V
#3060000000000000
b11 1
0V
#3070000000000000
1V
#3080000000000000
b11 1
0V
#3090000000000000
1V
#3100000000000000
b11 1
0V
#3110000000000000
1V
#3120000000000000
b11 1
0V
#3130000000000000
1V
#3140000000000000
b11 1
0V
#3150000000000000
1V
#3160000000000000
b11 1
0V
#3170000000000000
1V
#3180000000000000
b11 1
0V
#3190000000000000
1V
#3200000000000000
b11 1
0V
#3210000000000000
1V
#3220000000000000
b11 1
0V
#3230000000000000
1V
#3240000000000000
b11 1
0V
#3250000000000000
1V
#3260000000000000
b11 1
0V
#3270000000000000
1V
#3280000000000000
b11 1
0V
#3290000000000000
1V
#3300000000000000
b11 1
0V
#3310000000000000
1V
#3320000000000000
b11 1
0V
#3330000000000000
1V
#3340000000000000
b11 1
0V
#3350000000000000
1V
#3360000000000000
b11 1
0V
#3370000000000000
1V
#3380000000000000
b11 1
0V
#3390000000000000
1V
#3400000000000000
b11 1
0V
#3410000000000000
1V
#3420000000000000
b11 1
0V
#3430000000000000
1V
#3440000000000000
b11 1
0V
#3450000000000000
1V
#3460000000000000
b11 1
0V
#3470000000000000
1V
#3480000000000000
b11 1
0V
#3490000000000000
1V
#3500000000000000
b11 1
0V
#3510000000000000
1V
#3520000000000000
b11 1
0V
#3530000000000000
1V
#3540000000000000
b11 1
0V
#3550000000000000
1V
#3560000000000000
b11 1
0V
#3570000000000000
1V
#3580000000000000
b11 1
0V
#3590000000000000
1V
#3600000000000000
b11 1
0V
#3610000000000000
1V
#3620000000000000
b11 1
0V
#3630000000000000
1V
#3640000000000000
b11 1
0V
#3650000000000000
1V
#3660000000000000
b11 1
0V
#3670000000000000
1V
#3680000000000000
b11 1
0V
#3690000000000000
1V
#3700000000000000
b11 1
0V
#3710000000000000
1V
#3720000000000000
b11 1
0V
#3730000000000000
1V
#3740000000000000
b11 1
0V
#3750000000000000
1V
#3760000000000000
b11 1
0V
#3770000000000000
1V
#3780000000000000
b11 1
0V
#3790000000000000
1V
#3800000000000000
b11 1
0V
#3810000000000000
1V
#3820000000000000
b11 1
0V
#3830000000000000
1V
#3840000000000000
b11 1
0V
#3850000000000000
1V
#3860000000000000
b11 1
0V
#3870000000000000
1V
#3880000000000000
b11 1
0V
#3890000000000000
1V
#3900000000000000
b11 1
0V
#3910000000000000
1V
#3920000000000000
b11 1
0V
#3930000000000000
1V
#3940000000000000
b11 1
0V
#3950000000000000
1V
#3960000000000000
b11 1
0V
#3970000000000000
1V
#3980000000000000
b11 1
0V
#3990000000000000
1V
#4000000000000000
b11 1
0V
#4010000000000000
1V
#4020000000000000
b11 1
0V
#4030000000000000
1V
#4040000000000000
b11 1
0V
#4050000000000000
1V
#4060000000000000
b11 1
0V
#4070000000000000
1V
#4080000000000000
b11 1
0V
#4090000000000000
1V
#4100000000000000
b11 1
0V
#4110000000000000
1V
#4120000000000000
b11 1
0V
#4130000000000000
1V
#4140000000000000
b11 1
0V
#4150000000000000
1V
#4160000000000000
b11 1
0V
#4170000000000000
1V
#4180000000000000
b11 1
0V
#4190000000000000
1V
#4200000000000000
b11 1
0V
#4210000000000000
1V
#4220000000000000
b11 1
0V
#4230000000000000
1V
#4240000000000000
b11 1
0V
#4250000000000000
1V
#4260000000000000
b11 1
0V
#4270000000000000
1V
#4280000000000000
b11 1
0V
#4290000000000000
1V
#4300000000000000
b11 1
0V
#4310000000000000
1V
#4320000000000000
b11 1
0V
#4330000000000000
1V
#4340000000000000
b11 1
0V
#4350000000000000
1V
#4360000000000000
b11 1
0V
#4370000000000000
1V
#4380000000000000
b11 1
0V
#4390000000000000
1V
#4400000000000000
b11 1
0V
#4410000000000000
1V
#4420000000000000
b11 1
0V
#4430000000000000
1V
#4440000000000000
b11 1
0V
#4450000000000000
1V
#4460000000000000
b11 1
0V
#4470000000000000
1V
#4480000000000000
b11 1
0V
#4490000000000000
1V
#4500000000000000
b11 1
0V
