testTimer.v
module testTimer(input clock, output newclk);
    reg pixCounter = 0;      // Pixel counter to divide the clock
    assign newclk = pixCounter; // Set the clock high whenever the second bit (2) is high
	always @(posedge clock) begin
		pixCounter <= pixCounter + 1; // Since the reg is only 3 bits, it will reset every 8 cycles
	end

endmodule

testTimer_tb.v
`timescale 1 ns/ 100 ps
module testTimer_tb();
    reg clock;
    wire newclk;

    testTimer divTime(.clock(clock), .newclk(newclk));
    initial begin
        clock = 0;
        
        //Set a time delay, in nanoseconds
        #50000;

        //Ends the testbench
        $finish;
    end

    always  
        #10 clock = ~clock;

    initial begin
        //output filename
        $dumpfile("testTimer.vcd");
        // Module to capture and what level, 0 means all wires
        $dumpvars(0, testTimer_tb);
    end

endmodule

testTimer.vcd
$date
	Wed Nov  4 17:28:14 2020
$end
$version
	Icarus Verilog
$end
$timescale
	100ps
$end
$scope module testTimer_tb $end
$var wire 1 ! newclk $end
$var reg 1 " clock $end
$scope module divTime $end
$var wire 1 " clock $end
$var wire 1 ! newclk $end
$var reg 1 # pixCounter $end
$upscope $end
$upscope $end
$enddefinitions $end
#0
$dumpvars
0#
0"
0!
$end
#100
1!
1#
1"
#200
0"
#300
0!
0#
1"
#400
0"
#500
1!
1#
1"
#600
0"
#700
0!
0#
1"
#800
0"
#900
1!
1#
1"
#1000
0"
#1100
0!
0#
1"
#1200
0"
#1300
1!
1#
1"
#1400
0"
#1500
0!
0#
1"
#1600
0"
#1700
1!
1#
1"
#1800
0"
#1900
0!
0#
1"
#2000
0"
#2100
1!
1#
1"
#2200
0"
#2300
0!
0#
1"
#2400
0"
#2500
1!
1#
1"
#2600
0"
#2700
0!
0#
1"
#2800
0"
#2900
1!
1#
1"
#3000
0"
#3100
0!
0#
1"
#3200
0"
#3300
1!
1#
1"
#3400
0"
#3500
0!
0#
1"
#3600
0"
#3700
1!
1#
1"
#3800
0"
#3900
0!
0#
1"
#4000
0"
#4100
1!
1#
1"
#4200
0"
#4300
0!
0#
1"
#4400
0"
#4500
1!
1#
1"
#4600
0"
#4700
0!
0#
1"
#4800
0"
#4900
1!
1#
1"
#5000
0"
#5100
0!
0#
1"
#5200
0"
#5300
1!
1#
1"
#5400
0"
#5500
0!
0#
1"
#5600
0"
#5700
1!
1#
1"
#5800
0"
#5900
0!
0#
1"
#6000
0"
#6100
1!
1#
1"
#6200
0"
#6300
0!
0#
1"
#6400
0"
#6500
1!
1#
1"
#6600
0"
#6700
0!
0#
1"
#6800
0"
#6900
1!
1#
1"
#7000
0"
#7100
0!
0#
1"
#7200
0"
#7300
1!
1#
1"
#7400
0"
#7500
0!
0#
1"
#7600
0"
#7700
1!
1#
1"
#7800
0"
#7900
0!
0#
1"
#8000
0"
#8100
1!
1#
1"
#8200
0"
#8300
0!
0#
1"
#8400
0"
#8500
1!
1#
1"
#8600
0"
#8700
0!
0#
1"
#8800
0"
#8900
1!
1#
1"
#9000
0"
#9100
0!
0#
1"
#9200
0"
#9300
1!
1#
1"
#9400
0"
#9500
0!
0#
1"
#9600
0"
#9700
1!
1#
1"
#9800
0"
#9900
0!
0#
1"
#10000
0"
#10100
1!
1#
1"
#10200
0"
#10300
0!
0#
1"
#10400
0"
#10500
1!
1#
1"
#10600
0"
#10700
0!
0#
1"
#10800
0"
#10900
1!
1#
1"
#11000
0"
#11100
0!
0#
1"
#11200
0"
#11300
1!
1#
1"
#11400
0"
#11500
0!
0#
1"
#11600
0"
#11700
1!
1#
1"
#11800
0"
#11900
0!
0#
1"
#12000
0"
#12100
1!
1#
1"
#12200
0"
#12300
0!
0#
1"
#12400
0"
#12500
1!
1#
1"
#12600
0"
#12700
0!
0#
1"
#12800
0"
#12900
1!
1#
1"
#13000
0"
#13100
0!
0#
1"
#13200
0"
#13300
1!
1#
1"
#13400
0"
#13500
0!
0#
1"
#13600
0"
#13700
1!
1#
1"
#13800
0"
#13900
0!
0#
1"
#14000
0"
#14100
1!
1#
1"
#14200
0"
#14300
0!
0#
1"
#14400
0"
#14500
1!
1#
1"
#14600
0"
#14700
0!
0#
1"
#14800
0"
#14900
1!
1#
1"
#15000
0"
#15100
0!
0#
1"
#15200
0"
#15300
1!
1#
1"
#15400
0"
#15500
0!
0#
1"
#15600
0"
#15700
1!
1#
1"
#15800
0"
#15900
0!
0#
1"
#16000
0"
#16100
1!
1#
1"
#16200
0"
#16300
0!
0#
1"
#16400
0"
#16500
1!
1#
1"
#16600
0"
#16700
0!
0#
1"
#16800
0"
#16900
1!
1#
1"
#17000
0"
#17100
0!
0#
1"
#17200
0"
#17300
1!
1#
1"
#17400
0"
#17500
0!
0#
1"
#17600
0"
#17700
1!
1#
1"
#17800
0"
#17900
0!
0#
1"
#18000
0"
#18100
1!
1#
1"
#18200
0"
#18300
0!
0#
1"
#18400
0"
#18500
1!
1#
1"
#18600
0"
#18700
0!
0#
1"
#18800
0"
#18900
1!
1#
1"
#19000
0"
#19100
0!
0#
1"
#19200
0"
#19300
1!
1#
1"
#19400
0"
#19500
0!
0#
1"
#19600
0"
#19700
1!
1#
1"
#19800
0"
#19900
0!
0#
1"
#20000
0"
#20100
1!
1#
1"
#20200
0"
#20300
0!
0#
1"
#20400
0"
#20500
1!
1#
1"
#20600
0"
#20700
0!
0#
1"
#20800
0"
#20900
1!
1#
1"
#21000
0"
#21100
0!
0#
1"
#21200
0"
#21300
1!
1#
1"
#21400
0"
#21500
0!
0#
1"
#21600
0"
#21700
1!
1#
1"
#21800
0"
#21900
0!
0#
1"
#22000
0"
#22100
1!
1#
1"
#22200
0"
#22300
0!
0#
1"
#22400
0"
#22500
1!
1#
1"
#22600
0"
#22700
0!
0#
1"
#22800
0"
#22900
1!
1#
1"
#23000
0"
#23100
0!
0#
1"
#23200
0"
#23300
1!
1#
1"
#23400
0"
#23500
0!
0#
1"
#23600
0"
#23700
1!
1#
1"
#23800
0"
#23900
0!
0#
1"
#24000
0"
#24100
1!
1#
1"
#24200
0"
#24300
0!
0#
1"
#24400
0"
#24500
1!
1#
1"
#24600
0"
#24700
0!
0#
1"
#24800
0"
#24900
1!
1#
1"
#25000
0"
#25100
0!
0#
1"
#25200
0"
#25300
1!
1#
1"
#25400
0"
#25500
0!
0#
1"
#25600
0"
#25700
1!
1#
1"
#25800
0"
#25900
0!
0#
1"
#26000
0"
#26100
1!
1#
1"
#26200
0"
#26300
0!
0#
1"
#26400
0"
#26500
1!
1#
1"
#26600
0"
#26700
0!
0#
1"
#26800
0"
#26900
1!
1#
1"
#27000
0"
#27100
0!
0#
1"
#27200
0"
#27300
1!
1#
1"
#27400
0"
#27500
0!
0#
1"
#27600
0"
#27700
1!
1#
1"
#27800
0"
#27900
0!
0#
1"
#28000
0"
#28100
1!
1#
1"
#28200
0"
#28300
0!
0#
1"
#28400
0"
#28500
1!
1#
1"
#28600
0"
#28700
0!
0#
1"
#28800
0"
#28900
1!
1#
1"
#29000
0"
#29100
0!
0#
1"
#29200
0"
#29300
1!
1#
1"
#29400
0"
#29500
0!
0#
1"
#29600
0"
#29700
1!
1#
1"
#29800
0"
#29900
0!
0#
1"
#30000
0"
#30100
1!
1#
1"
#30200
0"
#30300
0!
0#
1"
#30400
0"
#30500
1!
1#
1"
#30600
0"
#30700
0!
0#
1"
#30800
0"
#30900
1!
1#
1"
#31000
0"
#31100
0!
0#
1"
#31200
0"
#31300
1!
1#
1"
#31400
0"
#31500
0!
0#
1"
#31600
0"
#31700
1!
1#
1"
#31800
0"
#31900
0!
0#
1"
#32000
0"
#32100
1!
1#
1"
#32200
0"
#32300
0!
0#
1"
#32400
0"
#32500
1!
1#
1"
#32600
0"
#32700
0!
0#
1"
#32800
0"
#32900
1!
1#
1"
#33000
0"
#33100
0!
0#
1"
#33200
0"
#33300
1!
1#
1"
#33400
0"
#33500
0!
0#
1"
#33600
0"
#33700
1!
1#
1"
#33800
0"
#33900
0!
0#
1"
#34000
0"
#34100
1!
1#
1"
#34200
0"
#34300
0!
0#
1"
#34400
0"
#34500
1!
1#
1"
#34600
0"
#34700
0!
0#
1"
#34800
0"
#34900
1!
1#
1"
#35000
0"
#35100
0!
0#
1"
#35200
0"
#35300
1!
1#
1"
#35400
0"
#35500
0!
0#
1"
#35600
0"
#35700
1!
1#
1"
#35800
0"
#35900
0!
0#
1"
#36000
0"
#36100
1!
1#
1"
#36200
0"
#36300
0!
0#
1"
#36400
0"
#36500
1!
1#
1"
#36600
0"
#36700
0!
0#
1"
#36800
0"
#36900
1!
1#
1"
#37000
0"
#37100
0!
0#
1"
#37200
0"
#37300
1!
1#
1"
#37400
0"
#37500
0!
0#
1"
#37600
0"
#37700
1!
1#
1"
#37800
0"
#37900
0!
0#
1"
#38000
0"
#38100
1!
1#
1"
#38200
0"
#38300
0!
0#
1"
#38400
0"
#38500
1!
1#
1"
#38600
0"
#38700
0!
0#
1"
#38800
0"
#38900
1!
1#
1"
#39000
0"
#39100
0!
0#
1"
#39200
0"
#39300
1!
1#
1"
#39400
0"
#39500
0!
0#
1"
#39600
0"
#39700
1!
1#
1"
#39800
0"
#39900
0!
0#
1"
#40000
0"
#40100
1!
1#
1"
#40200
0"
#40300
0!
0#
1"
#40400
0"
#40500
1!
1#
1"
#40600
0"
#40700
0!
0#
1"
#40800
0"
#40900
1!
1#
1"
#41000
0"
#41100
0!
0#
1"
#41200
0"
#41300
1!
1#
1"
#41400
0"
#41500
0!
0#
1"
#41600
0"
#41700
1!
1#
1"
#41800
0"
#41900
0!
0#
1"
#42000
0"
#42100
1!
1#
1"
#42200
0"
#42300
0!
0#
1"
#42400
0"
#42500
1!
1#
1"
#42600
0"
#42700
0!
0#
1"
#42800
0"
#42900
1!
1#
1"
#43000
0"
#43100
0!
0#
1"
#43200
0"
#43300
1!
1#
1"
#43400
0"
#43500
0!
0#
1"
#43600
0"
#43700
1!
1#
1"
#43800
0"
#43900
0!
0#
1"
#44000
0"
#44100
1!
1#
1"
#44200
0"
#44300
0!
0#
1"
#44400
0"
#44500
1!
1#
1"
#44600
0"
#44700
0!
0#
1"
#44800
0"
#44900
1!
1#
1"
#45000
0"
#45100
0!
0#
1"
#45200
0"
#45300
1!
1#
1"
#45400
0"
#45500
0!
0#
1"
#45600
0"
#45700
1!
1#
1"
#45800
0"
#45900
0!
0#
1"
#46000
0"
#46100
1!
1#
1"
#46200
0"
#46300
0!
0#
1"
#46400
0"
#46500
1!
1#
1"
#46600
0"
#46700
0!
0#
1"
#46800
0"
#46900
1!
1#
1"
#47000
0"
#47100
0!
0#
1"
#47200
0"
#47300
1!
1#
1"
#47400
0"
#47500
0!
0#
1"
#47600
0"
#47700
1!
1#
1"
#47800
0"
#47900
0!
0#
1"
#48000
0"
#48100
1!
1#
1"
#48200
0"
#48300
0!
0#
1"
#48400
0"
#48500
1!
1#
1"
#48600
0"
#48700
0!
0#
1"
#48800
0"
#48900
1!
1#
1"
#49000
0"
#49100
0!
0#
1"
#49200
0"
#49300
1!
1#
1"
#49400
0"
#49500
0!
0#
1"
#49600
0"
#49700
1!
1#
1"
#49800
0"
#49900
0!
0#
1"
#50000
0"
#50100
1!
1#
1"
#50200
0"
#50300
0!
0#
1"
#50400
0"
#50500
1!
1#
1"
#50600
0"
#50700
0!
0#
1"
#50800
0"
#50900
1!
1#
1"
#51000
0"
#51100
0!
0#
1"
#51200
0"
#51300
1!
1#
1"
#51400
0"
#51500
0!
0#
1"
#51600
0"
#51700
1!
1#
1"
#51800
0"
#51900
0!
0#
1"
#52000
0"
#52100
1!
1#
1"
#52200
0"
#52300
0!
0#
1"
#52400
0"
#52500
1!
1#
1"
#52600
0"
#52700
0!
0#
1"
#52800
0"
#52900
1!
1#
1"
#53000
0"
#53100
0!
0#
1"
#53200
0"
#53300
1!
1#
1"
#53400
0"
#53500
0!
0#
1"
#53600
0"
#53700
1!
1#
1"
#53800
0"
#53900
0!
0#
1"
#54000
0"
#54100
1!
1#
1"
#54200
0"
#54300
0!
0#
1"
#54400
0"
#54500
1!
1#
1"
#54600
0"
#54700
0!
0#
1"
#54800
0"
#54900
1!
1#
1"
#55000
0"
#55100
0!
0#
1"
#55200
0"
#55300
1!
1#
1"
#55400
0"
#55500
0!
0#
1"
#55600
0"
#55700
1!
1#
1"
#55800
0"
#55900
0!
0#
1"
#56000
0"
#56100
1!
1#
1"
#56200
0"
#56300
0!
0#
1"
#56400
0"
#56500
1!
1#
1"
#56600
0"
#56700
0!
0#
1"
#56800
0"
#56900
1!
1#
1"
#57000
0"
#57100
0!
0#
1"
#57200
0"
#57300
1!
1#
1"
#57400
0"
#57500
0!
0#
1"
#57600
0"
#57700
1!
1#
1"
#57800
0"
#57900
0!
0#
1"
#58000
0"
#58100
1!
1#
1"
#58200
0"
#58300
0!
0#
1"
#58400
0"
#58500
1!
1#
1"
#58600
0"
#58700
0!
0#
1"
#58800
0"
#58900
1!
1#
1"
#59000
0"
#59100
0!
0#
1"
#59200
0"
#59300
1!
1#
1"
#59400
0"
#59500
0!
0#
1"
#59600
0"
#59700
1!
1#
1"
#59800
0"
#59900
0!
0#
1"
#60000
0"
#60100
1!
1#
1"
#60200
0"
#60300
0!
0#
1"
#60400
0"
#60500
1!
1#
1"
#60600
0"
#60700
0!
0#
1"
#60800
0"
#60900
1!
1#
1"
#61000
0"
#61100
0!
0#
1"
#61200
0"
#61300
1!
1#
1"
#61400
0"
#61500
0!
0#
1"
#61600
0"
#61700
1!
1#
1"
#61800
0"
#61900
0!
0#
1"
#62000
0"
#62100
1!
1#
1"
#62200
0"
#62300
0!
0#
1"
#62400
0"
#62500
1!
1#
1"
#62600
0"
#62700
0!
0#
1"
#62800
0"
#62900
1!
1#
1"
#63000
0"
#63100
0!
0#
1"
#63200
0"
#63300
1!
1#
1"
#63400
0"
#63500
0!
0#
1"
#63600
0"
#63700
1!
1#
1"
#63800
0"
#63900
0!
0#
1"
#64000
0"
#64100
1!
1#
1"
#64200
0"
#64300
0!
0#
1"
#64400
0"
#64500
1!
1#
1"
#64600
0"
#64700
0!
0#
1"
#64800
0"
#64900
1!
1#
1"
#65000
0"
#65100
0!
0#
1"
#65200
0"
#65300
1!
1#
1"
#65400
0"
#65500
0!
0#
1"
#65600
0"
#65700
1!
1#
1"
#65800
0"
#65900
0!
0#
1"
#66000
0"
#66100
1!
1#
1"
#66200
0"
#66300
0!
0#
1"
#66400
0"
#66500
1!
1#
1"
#66600
0"
#66700
0!
0#
1"
#66800
0"
#66900
1!
1#
1"
#67000
0"
#67100
0!
0#
1"
#67200
0"
#67300
1!
1#
1"
#67400
0"
#67500
0!
0#
1"
#67600
0"
#67700
1!
1#
1"
#67800
0"
#67900
0!
0#
1"
#68000
0"
#68100
1!
1#
1"
#68200
0"
#68300
0!
0#
1"
#68400
0"
#68500
1!
1#
1"
#68600
0"
#68700
0!
0#
1"
#68800
0"
#68900
1!
1#
1"
#69000
0"
#69100
0!
0#
1"
#69200
0"
#69300
1!
1#
1"
#69400
0"
#69500
0!
0#
1"
#69600
0"
#69700
1!
1#
1"
#69800
0"
#69900
0!
0#
1"
#70000
0"
#70100
1!
1#
1"
#70200
0"
#70300
0!
0#
1"
#70400
0"
#70500
1!
1#
1"
#70600
0"
#70700
0!
0#
1"
#70800
0"
#70900
1!
1#
1"
#71000
0"
#71100
0!
0#
1"
#71200
0"
#71300
1!
1#
1"
#71400
0"
#71500
0!
0#
1"
#71600
0"
#71700
1!
1#
1"
#71800
0"
#71900
0!
0#
1"
#72000
0"
#72100
1!
1#
1"
#72200
0"
#72300
0!
0#
1"
#72400
0"
#72500
1!
1#
1"
#72600
0"
#72700
0!
0#
1"
#72800
0"
#72900
1!
1#
1"
#73000
0"
#73100
0!
0#
1"
#73200
0"
#73300
1!
1#
1"
#73400
0"
#73500
0!
0#
1"
#73600
0"
#73700
1!
1#
1"
#73800
0"
#73900
0!
0#
1"
#74000
0"
#74100
1!
1#
1"
#74200
0"
#74300
0!
0#
1"
#74400
0"
#74500
1!
1#
1"
#74600
0"
#74700
0!
0#
1"
#74800
0"
#74900
1!
1#
1"
#75000
0"
#75100
0!
0#
1"
#75200
0"
#75300
1!
1#
1"
#75400
0"
#75500
0!
0#
1"
#75600
0"
#75700
1!
1#
1"
#75800
0"
#75900
0!
0#
1"
#76000
0"
#76100
1!
1#
1"
#76200
0"
#76300
0!
0#
1"
#76400
0"
#76500
1!
1#
1"
#76600
0"
#76700
0!
0#
1"
#76800
0"
#76900
1!
1#
1"
#77000
0"
#77100
0!
0#
1"
#77200
0"
#77300
1!
1#
1"
#77400
0"
#77500
0!
0#
1"
#77600
0"
#77700
1!
1#
1"
#77800
0"
#77900
0!
0#
1"
#78000
0"
#78100
1!
1#
1"
#78200
0"
#78300
0!
0#
1"
#78400
0"
#78500
1!
1#
1"
#78600
0"
#78700
0!
0#
1"
#78800
0"
#78900
1!
1#
1"
#79000
0"
#79100
0!
0#
1"
#79200
0"
#79300
1!
1#
1"
#79400
0"
#79500
0!
0#
1"
#79600
0"
#79700
1!
1#
1"
#79800
0"
#79900
0!
0#
1"
#80000
0"
#80100
1!
1#
1"
#80200
0"
#80300
0!
0#
1"
#80400
0"
#80500
1!
1#
1"
#80600
0"
#80700
0!
0#
1"
#80800
0"
#80900
1!
1#
1"
#81000
0"
#81100
0!
0#
1"
#81200
0"
#81300
1!
1#
1"
#81400
0"
#81500
0!
0#
1"
#81600
0"
#81700
1!
1#
1"
#81800
0"
#81900
0!
0#
1"
#82000
0"
#82100
1!
1#
1"
#82200
0"
#82300
0!
0#
1"
#82400
0"
#82500
1!
1#
1"
#82600
0"
#82700
0!
0#
1"
#82800
0"
#82900
1!
1#
1"
#83000
0"
#83100
0!
0#
1"
#83200
0"
#83300
1!
1#
1"
#83400
0"
#83500
0!
0#
1"
#83600
0"
#83700
1!
1#
1"
#83800
0"
#83900
0!
0#
1"
#84000
0"
#84100
1!
1#
1"
#84200
0"
#84300
0!
0#
1"
#84400
0"
#84500
1!
1#
1"
#84600
0"
#84700
0!
0#
1"
#84800
0"
#84900
1!
1#
1"
#85000
0"
#85100
0!
0#
1"
#85200
0"
#85300
1!
1#
1"
#85400
0"
#85500
0!
0#
1"
#85600
0"
#85700
1!
1#
1"
#85800
0"
#85900
0!
0#
1"
#86000
0"
#86100
1!
1#
1"
#86200
0"
#86300
0!
0#
1"
#86400
0"
#86500
1!
1#
1"
#86600
0"
#86700
0!
0#
1"
#86800
0"
#86900
1!
1#
1"
#87000
0"
#87100
0!
0#
1"
#87200
0"
#87300
1!
1#
1"
#87400
0"
#87500
0!
0#
1"
#87600
0"
#87700
1!
1#
1"
#87800
0"
#87900
0!
0#
1"
#88000
0"
#88100
1!
1#
1"
#88200
0"
#88300
0!
0#
1"
#88400
0"
#88500
1!
1#
1"
#88600
0"
#88700
0!
0#
1"
#88800
0"
#88900
1!
1#
1"
#89000
0"
#89100
0!
0#
1"
#89200
0"
#89300
1!
1#
1"
#89400
0"
#89500
0!
0#
1"
#89600
0"
#89700
1!
1#
1"
#89800
0"
#89900
0!
0#
1"
#90000
0"
#90100
1!
1#
1"
#90200
0"
#90300
0!
0#
1"
#90400
0"
#90500
1!
1#
1"
#90600
0"
#90700
0!
0#
1"
#90800
0"
#90900
1!
1#
1"
#91000
0"
#91100
0!
0#
1"
#91200
0"
#91300
1!
1#
1"
#91400
0"
#91500
0!
0#
1"
#91600
0"
#91700
1!
1#
1"
#91800
0"
#91900
0!
0#
1"
#92000
0"
#92100
1!
1#
1"
#92200
0"
#92300
0!
0#
1"
#92400
0"
#92500
1!
1#
1"
#92600
0"
#92700
0!
0#
1"
#92800
0"
#92900
1!
1#
1"
#93000
0"
#93100
0!
0#
1"
#93200
0"
#93300
1!
1#
1"
#93400
0"
#93500
0!
0#
1"
#93600
0"
#93700
1!
1#
1"
#93800
0"
#93900
0!
0#
1"
#94000
0"
#94100
1!
1#
1"
#94200
0"
#94300
0!
0#
1"
#94400
0"
#94500
1!
1#
1"
#94600
0"
#94700
0!
0#
1"
#94800
0"
#94900
1!
1#
1"
#95000
0"
#95100
0!
0#
1"
#95200
0"
#95300
1!
1#
1"
#95400
0"
#95500
0!
0#
1"
#95600
0"
#95700
1!
1#
1"
#95800
0"
#95900
0!
0#
1"
#96000
0"
#96100
1!
1#
1"
#96200
0"
#96300
0!
0#
1"
#96400
0"
#96500
1!
1#
1"
#96600
0"
#96700
0!
0#
1"
#96800
0"
#96900
1!
1#
1"
#97000
0"
#97100
0!
0#
1"
#97200
0"
#97300
1!
1#
1"
#97400
0"
#97500
0!
0#
1"
#97600
0"
#97700
1!
1#
1"
#97800
0"
#97900
0!
0#
1"
#98000
0"
#98100
1!
1#
1"
#98200
0"
#98300
0!
0#
1"
#98400
0"
#98500
1!
1#
1"
#98600
0"
#98700
0!
0#
1"
#98800
0"
#98900
1!
1#
1"
#99000
0"
#99100
0!
0#
1"
#99200
0"
#99300
1!
1#
1"
#99400
0"
#99500
0!
0#
1"
#99600
0"
#99700
1!
1#
1"
#99800
0"
#99900
0!
0#
1"
#100000
0"
#100100
1!
1#
1"
#100200
0"
#100300
0!
0#
1"
#100400
0"
#100500
1!
1#
1"
#100600
0"
#100700
0!
0#
1"
#100800
0"
#100900
1!
1#
1"
#101000
0"
#101100
0!
0#
1"
#101200
0"
#101300
1!
1#
1"
#101400
0"
#101500
0!
0#
1"
#101600
0"
#101700
1!
1#
1"
#101800
0"
#101900
0!
0#
1"
#102000
0"
#102100
1!
1#
1"
#102200
0"
#102300
0!
0#
1"
#102400
0"
#102500
1!
1#
1"
#102600
0"
#102700
0!
0#
1"
#102800
0"
#102900
1!
1#
1"
#103000
0"
#103100
0!
0#
1"
#103200
0"
#103300
1!
1#
1"
#103400
0"
#103500
0!
0#
1"
#103600
0"
#103700
1!
1#
1"
#103800
0"
#103900
0!
0#
1"
#104000
0"
#104100
1!
1#
1"
#104200
0"
#104300
0!
0#
1"
#104400
0"
#104500
1!
1#
1"
#104600
0"
#104700
0!
0#
1"
#104800
0"
#104900
1!
1#
1"
#105000
0"
#105100
0!
0#
1"
#105200
0"
#105300
1!
1#
1"
#105400
0"
#105500
0!
0#
1"
#105600
0"
#105700
1!
1#
1"
#105800
0"
#105900
0!
0#
1"
#106000
0"
#106100
1!
1#
1"
#106200
0"
#106300
0!
0#
1"
#106400
0"
#106500
1!
1#
1"
#106600
0"
#106700
0!
0#
1"
#106800
0"
#106900
1!
1#
1"
#107000
0"
#107100
0!
0#
1"
#107200
0"
#107300
1!
1#
1"
#107400
0"
#107500
0!
0#
1"
#107600
0"
#107700
1!
1#
1"
#107800
0"
#107900
0!
0#
1"
#108000
0"
#108100
1!
1#
1"
#108200
0"
#108300
0!
0#
1"
#108400
0"
#108500
1!
1#
1"
#108600
0"
#108700
0!
0#
1"
#108800
0"
#108900
1!
1#
1"
#109000
0"
#109100
0!
0#
1"
#109200
0"
#109300
1!
1#
1"
#109400
0"
#109500
0!
0#
1"
#109600
0"
#109700
1!
1#
1"
#109800
0"
#109900
0!
0#
1"
#110000
0"
#110100
1!
1#
1"
#110200
0"
#110300
0!
0#
1"
#110400
0"
#110500
1!
1#
1"
#110600
0"
#110700
0!
0#
1"
#110800
0"
#110900
1!
1#
1"
#111000
0"
#111100
0!
0#
1"
#111200
0"
#111300
1!
1#
1"
#111400
0"
#111500
0!
0#
1"
#111600
0"
#111700
1!
1#
1"
#111800
0"
#111900
0!
0#
1"
#112000
0"
#112100
1!
1#
1"
#112200
0"
#112300
0!
0#
1"
#112400
0"
#112500
1!
1#
1"
#112600
0"
#112700
0!
0#
1"
#112800
0"
#112900
1!
1#
1"
#113000
0"
#113100
0!
0#
1"
#113200
0"
#113300
1!
1#
1"
#113400
0"
#113500
0!
0#
1"
#113600
0"
#113700
1!
1#
1"
#113800
0"
#113900
0!
0#
1"
#114000
0"
#114100
1!
1#
1"
#114200
0"
#114300
0!
0#
1"
#114400
0"
#114500
1!
1#
1"
#114600
0"
#114700
0!
0#
1"
#114800
0"
#114900
1!
1#
1"
#115000
0"
#115100
0!
0#
1"
#115200
0"
#115300
1!
1#
1"
#115400
0"
#115500
0!
0#
1"
#115600
0"
#115700
1!
1#
1"
#115800
0"
#115900
0!
0#
1"
#116000
0"
#116100
1!
1#
1"
#116200
0"
#116300
0!
0#
1"
#116400
0"
#116500
1!
1#
1"
#116600
0"
#116700
0!
0#
1"
#116800
0"
#116900
1!
1#
1"
#117000
0"
#117100
0!
0#
1"
#117200
0"
#117300
1!
1#
1"
#117400
0"
#117500
0!
0#
1"
#117600
0"
#117700
1!
1#
1"
#117800
0"
#117900
0!
0#
1"
#118000
0"
#118100
1!
1#
1"
#118200
0"
#118300
0!
0#
1"
#118400
0"
#118500
1!
1#
1"
#118600
0"
#118700
0!
0#
1"
#118800
0"
#118900
1!
1#
1"
#119000
0"
#119100
0!
0#
1"
#119200
0"
#119300
1!
1#
1"
#119400
0"
#119500
0!
0#
1"
#119600
0"
#119700
1!
1#
1"
#119800
0"
#119900
0!
0#
1"
#120000
0"
#120100
1!
1#
1"
#120200
0"
#120300
0!
0#
1"
#120400
0"
#120500
1!
1#
1"
#120600
0"
#120700
0!
0#
1"
#120800
0"
#120900
1!
1#
1"
#121000
0"
#121100
0!
0#
1"
#121200
0"
#121300
1!
1#
1"
#121400
0"
#121500
0!
0#
1"
#121600
0"
#121700
1!
1#
1"
#121800
0"
#121900
0!
0#
1"
#122000
0"
#122100
1!
1#
1"
#122200
0"
#122300
0!
0#
1"
#122400
0"
#122500
1!
1#
1"
#122600
0"
#122700
0!
0#
1"
#122800
0"
#122900
1!
1#
1"
#123000
0"
#123100
0!
0#
1"
#123200
0"
#123300
1!
1#
1"
#123400
0"
#123500
0!
0#
1"
#123600
0"
#123700
1!
1#
1"
#123800
0"
#123900
0!
0#
1"
#124000
0"
#124100
1!
1#
1"
#124200
0"
#124300
0!
0#
1"
#124400
0"
#124500
1!
1#
1"
#124600
0"
#124700
0!
0#
1"
#124800
0"
#124900
1!
1#
1"
#125000
0"
#125100
0!
0#
1"
#125200
0"
#125300
1!
1#
1"
#125400
0"
#125500
0!
0#
1"
#125600
0"
#125700
1!
1#
1"
#125800
0"
#125900
0!
0#
1"
#126000
0"
#126100
1!
1#
1"
#126200
0"
#126300
0!
0#
1"
#126400
0"
#126500
1!
1#
1"
#126600
0"
#126700
0!
0#
1"
#126800
0"
#126900
1!
1#
1"
#127000
0"
#127100
0!
0#
1"
#127200
0"
#127300
1!
1#
1"
#127400
0"
#127500
0!
0#
1"
#127600
0"
#127700
1!
1#
1"
#127800
0"
#127900
0!
0#
1"
#128000
0"
#128100
1!
1#
1"
#128200
0"
#128300
0!
0#
1"
#128400
0"
#128500
1!
1#
1"
#128600
0"
#128700
0!
0#
1"
#128800
0"
#128900
1!
1#
1"
#129000
0"
#129100
0!
0#
1"
#129200
0"
#129300
1!
1#
1"
#129400
0"
#129500
0!
0#
1"
#129600
0"
#129700
1!
1#
1"
#129800
0"
#129900
0!
0#
1"
#130000
0"
#130100
1!
1#
1"
#130200
0"
#130300
0!
0#
1"
#130400
0"
#130500
1!
1#
1"
#130600
0"
#130700
0!
0#
1"
#130800
0"
#130900
1!
1#
1"
#131000
0"
#131100
0!
0#
1"
#131200
0"
#131300
1!
1#
1"
#131400
0"
#131500
0!
0#
1"
#131600
0"
#131700
1!
1#
1"
#131800
0"
#131900
0!
0#
1"
#132000
0"
#132100
1!
1#
1"
#132200
0"
#132300
0!
0#
1"
#132400
0"
#132500
1!
1#
1"
#132600
0"
#132700
0!
0#
1"
#132800
0"
#132900
1!
1#
1"
#133000
0"
#133100
0!
0#
1"
#133200
0"
#133300
1!
1#
1"
#133400
0"
#133500
0!
0#
1"
#133600
0"
#133700
1!
1#
1"
#133800
0"
#133900
0!
0#
1"
#134000
0"
#134100
1!
1#
1"
#134200
0"
#134300
0!
0#
1"
#134400
0"
#134500
1!
1#
1"
#134600
0"
#134700
0!
0#
1"
#134800
0"
#134900
1!
1#
1"
#135000
0"
#135100
0!
0#
1"
#135200
0"
#135300
1!
1#
1"
#135400
0"
#135500
0!
0#
1"
#135600
0"
#135700
1!
1#
1"
#135800
0"
#135900
0!
0#
1"
#136000
0"
#136100
1!
1#
1"
#136200
0"
#136300
0!
0#
1"
#136400
0"
#136500
1!
1#
1"
#136600
0"
#136700
0!
0#
1"
#136800
0"
#136900
1!
1#
1"
#137000
0"
#137100
0!
0#
1"
#137200
0"
#137300
1!
1#
1"
#137400
0"
#137500
0!
0#
1"
#137600
0"
#137700
1!
1#
1"
#137800
0"
#137900
0!
0#
1"
#138000
0"
#138100
1!
1#
1"
#138200
0"
#138300
0!
0#
1"
#138400
0"
#138500
1!
1#
1"
#138600
0"
#138700
0!
0#
1"
#138800
0"
#138900
1!
1#
1"
#139000
0"
#139100
0!
0#
1"
#139200
0"
#139300
1!
1#
1"
#139400
0"
#139500
0!
0#
1"
#139600
0"
#139700
1!
1#
1"
#139800
0"
#139900
0!
0#
1"
#140000
0"
#140100
1!
1#
1"
#140200
0"
#140300
0!
0#
1"
#140400
0"
#140500
1!
1#
1"
#140600
0"
#140700
0!
0#
1"
#140800
0"
#140900
1!
1#
1"
#141000
0"
#141100
0!
0#
1"
#141200
0"
#141300
1!
1#
1"
#141400
0"
#141500
0!
0#
1"
#141600
0"
#141700
1!
1#
1"
#141800
0"
#141900
0!
0#
1"
#142000
0"
#142100
1!
1#
1"
#142200
0"
#142300
0!
0#
1"
#142400
0"
#142500
1!
1#
1"
#142600
0"
#142700
0!
0#
1"
#142800
0"
#142900
1!
1#
1"
#143000
0"
#143100
0!
0#
1"
#143200
0"
#143300
1!
1#
1"
#143400
0"
#143500
0!
0#
1"
#143600
0"
#143700
1!
1#
1"
#143800
0"
#143900
0!
0#
1"
#144000
0"
#144100
1!
1#
1"
#144200
0"
